[
  {
    "name": "contact",
    "path": "/contact",
    "component": "/home/rafael/Projetos/rafaelgaedke.com.br/pages/contact.vue",
    "chunkName": "pages/contact"
  },
  {
    "name": "portfolio",
    "path": "/portfolio",
    "component": "/home/rafael/Projetos/rafaelgaedke.com.br/pages/portfolio.vue",
    "chunkName": "pages/portfolio"
  },
  {
    "name": "resume",
    "path": "/resume",
    "component": "/home/rafael/Projetos/rafaelgaedke.com.br/pages/resume.vue",
    "chunkName": "pages/resume"
  },
  {
    "name": "api-hello",
    "path": "/api/hello",
    "component": "/home/rafael/Projetos/rafaelgaedke.com.br/pages/api/hello.js",
    "chunkName": "pages/api/hello"
  },
  {
    "name": "index",
    "path": "/",
    "component": "/home/rafael/Projetos/rafaelgaedke.com.br/pages/index.vue",
    "chunkName": "pages/index"
  },
  {
    "name": "app",
    "path": "/:app",
    "component": "/home/rafael/Projetos/rafaelgaedke.com.br/pages/_app.js",
    "chunkName": "pages/_app"
  }
]
